{
  "admin": [
    [
      "Alice",
      "a"
    ],
    [
      "Bob",
      "b"
    ],
    [
      "Curry",
      "c"
    ],
    [
      "\u738b\u4e8c\u72d7",
      "w"
    ],
    [
      "\u674e\u4e09\u86cb",
      "l"
    ],
    [
      "\u9648\u9e3f\u5b87",
      "c"
    ]
  ],
  "buy": [
    [
      "HK_TENCENT",
      10.2,
      100
    ],
    [
      "APPLE",
      1.2,
      24
    ],
    [
      "APPLE",
      1.2,
      24
    ],
    [
      "BMW",
      1.2,
      24
    ],
    [
      "\u7231\u5eb7\u79d1\u6280",
      2.3,
      30000
    ],
    [
      "\u6052\u5927\u9ad8\u65b0",
      120,
      24
    ],
    [
      "\u6052\u5927\u9ad8\u65b0",
      126,
      24
    ],
    [
      "\u6052\u5927\u9ad8\u65b0",
      112,
      24
    ],
    [
      "\u6052\u5927\u9ad8\u65b0",
      10,
      24
    ],
    [
      "\u6052\u5927\u9ad8\u65b0",
      120,
      25
    ],
    [
      "\u6052\u5927\u9ad8\u65b0",
      130,
      24
    ],
    [
      "\u6c38\u5b89\u884c",
      52.44,
      668
    ],
    [
      "CMCC",
      10,
      10
    ]
  ],
  "auth": [
    [
      "Alice",
      "APPLE"
    ],
    [
      "Alice",
      "CMCC"
    ],
    [
      "Alice",
      "\u7231\u5eb7\u79d1\u6280"
    ],
    [
      "Alice",
      "\u6c38\u5b89\u884c"
    ],
    [
      "Alice",
      "\u7535\u5de5\u5408\u91d1"
    ],
    [
      "Alice",
      "BMW"
    ],
    [
      "Alice",
      "\u6052\u5927\u9ad8\u65b0"
    ]
  ],
  "sell": [
    [
      "APPLE",
      1.2,
      24
    ],
    [
      "APPLE",
      1.2,
      24
    ],
    [
      "BMW",
      1.2,
      24
    ],
    [
      "\u7231\u5eb7\u79d1\u6280",
      2.3,
      30000
    ],
    [
      "\u6052\u5927\u9ad8\u65b0",
      120,
      24
    ],
    [
      "\u6c38\u5b89\u884c",
      52.44,
      668
    ],
    [
      "\u6052\u5927\u9ad8\u65b0",
      120,
      24
    ],
    [
      "\u6052\u5927\u9ad8\u65b0",
      10,
      4
    ],
    [
      "\u6052\u5927\u9ad8\u65b0",
      220,
      6
    ],
    [
      "\u6052\u5927\u9ad8\u65b0",
      121,
      9
    ],
    [
      "\u6052\u5927\u9ad8\u65b0",
      120,
      12
    ],
    [
      "CMCC",
      10,
      10
    ]
  ],
  "tran": [
    [
      "APPLE",
      1.2,
      24
    ],
    [
      "BMW",
      1.2,
      24
    ],
    [
      "\u7231\u5eb7\u79d1\u6280",
      2.3,
      30000
    ],
    [
      "\u6052\u5927\u9ad8\u65b0",
      120,
      24
    ],
    [
      "\u6052\u5927\u9ad8\u65b0",
      112,
      26
    ],
    [
      "\u6052\u5927\u9ad8\u65b0",
      20,
      60
    ],
    [
      "\u7535\u5de5\u5408\u91d1",
      12.2,
      260
    ]
  ],
  "stock": [
    [
      "APPLE"
    ],
    [
      "HK_TENCENT"
    ],
    [
      "CMCC"
    ],
    [
      "\u7231\u5eb7\u79d1\u6280"
    ],
    [
      "\u6c38\u5b89\u884c"
    ],
    [
      "\u7535\u5de5\u5408\u91d1"
    ],
    [
      "BMW"
    ],
    [
      "\u6052\u5927\u9ad8\u65b0"
    ]
  ]
}